{
    "name": "ATM_report_emails_clicks_msd",
    "description": "Old report activities - deprecated",
    "key": "7092899c-0dfe-0a80-b4c5-eebb8ccd51ec",
    "type": "scheduled",
    "status": "PausedSchedule",
    "schedule": {
        "startDate": "2019-03-15T06:00:00",
        "endDate": "2079-06-06T00:00:00",
        "icalRecur": "FREQ=DAILY;UNTIL=20790606T080000;INTERVAL=1",
        "timezoneName": "Romance Standard Time"
    },
    "steps": [
        {
            "name": "",
            "activities": [
                {
                    "name": "QRY_Intermediate_Sent",
                    "r__type": "query"
                },
                {
                    "name": "QRY_Intermediate_Open",
                    "r__type": "query"
                },
                {
                    "name": "QRY_Intermediate_Click",
                    "r__type": "query"
                }
            ]
        },
        {
            "name": "",
            "activities": [
                {
                    "name": "QRY_Report_Emails_Clicks_MSD_Spain",
                    "r__type": "query"
                }
            ]
        }
    ],
    "notifications": [
        {
            "email": [
                "dmcamseuramca@merck.com"
            ],
            "message": "",
            "type": "Complete"
        },
        {
            "email": [
                "dmcamseuramca@merck.com"
            ],
            "message": "",
            "type": "Error"
        }
    ],
    "r__folder_Path": "my automations/2.Business/3_REPORT"
}
