{
    "name": "JP_AS_open_2003_05",
    "description": "",
    "key": "514c5afc-d150-8e2b-0481-8ff9180fdae7",
    "type": "scheduled",
    "status": "PausedSchedule",
    "schedule": {
        "startDate": "2020-06-01T21:00:00",
        "endDate": "2020-06-01T21:00:00",
        "icalRecur": "FREQ=DAILY;COUNT=1;INTERVAL=1",
        "timezoneName": "Tokyo Standard Time"
    },
    "steps": [
        {
            "name": "",
            "activities": [
                {
                    "name": "JP_Q_open_2003",
                    "r__type": "query"
                }
            ]
        },
        {
            "name": "",
            "activities": [
                {
                    "name": "JP_Q_open_2004",
                    "r__type": "query"
                }
            ]
        },
        {
            "name": "",
            "activities": [
                {
                    "name": "JP_Q_open_2005",
                    "r__type": "query"
                }
            ]
        }
    ],
    "r__folder_Path": "my automations/japan/used/report_2005251200_BU"
}
