{
    "key": "3919ac8d-431b-323f-a28b-c3e20fcf4b97",
    "name": "Lung-Campaign-1_AE",
    "lastPublishedDate": "2023-06-05T22:18:33",
    "description": "",
    "version": 1,
    "workflowApiVersion": 1,
    "createdDate": "2023-06-04T23:26:37.653",
    "modifiedDate": "2023-06-05T22:18:33.71",
    "activities": [
        {
            "id": "77fbf7b6-0a16-4bcd-9651-f0ae47b7aa38",
            "key": "EMAILV2-1",
            "name": "PH_KEY_00888_Lung-Campaign-1_AE_SFMC-Summary-Adherence-EM1_BR_MOTF+All+EN",
            "description": "",
            "type": "EMAILV2",
            "outcomes": [
                {
                    "key": "c1179a30-02aa-4e45-be46-4ca08655099b",
                    "next": "WAITBYDURATION-5",
                    "arguments": {},
                    "metaData": {
                        "invalid": false
                    }
                }
            ],
            "arguments": {
                "activityId": "{{Activity.Id}}",
                "definitionId": "{{Context.DefinitionId}}",
                "emailSubjectDataBound": "Act now to help extend survival for your indicated mNSCLC patients",
                "contactId": "{{Contact.Id}}",
                "contactKey": "{{Contact.Key}}",
                "emailAddress": "{{InteractionDefaults.Email}}",
                "sourceCustomObjectId": "{{Contact.AddressInfo.Email.SourceCustomObjectId}}",
                "sourceCustomObjectKey": "{{Contact.AddressInfo.Email.SourceCustomObjectKey}}",
                "fieldType": "{{Contact.AddressInfo.Email.FieldType}}",
                "eventData": "{{Event}}",
                "obfuscationProperties": "{{InteractionDefaults.Email.ObfuscationProperties}}",
                "customObjectKey": "",
                "definitionInstanceId": "{{Context.DefinitionInstanceId}}"
            },
            "configurationArguments": {
                "triggeredSend": {
                    "autoAddSubscribers": true,
                    "autoUpdateSubscribers": true,
                    "bccEmail": "",
                    "campaigns": [
                        {
                            "id": 6061,
                            "name": "PH-Lung-Campaign-1",
                            "color": "#ffc7c7"
                        }
                    ],
                    "ccEmail": "",
                    "created": {
                        "name": "",
                        "date": ""
                    },
                    "domainExclusions": [],
                    "dynamicEmailSubject": "Act now to help extend survival for your indicated mNSCLC patients",
                    "emailId": 158284,
                    "emailSubject": "Act now to help extend survival for your indicated mNSCLC patients",
                    "exclusionFilter": "",
                    "isSalesforceTracking": false,
                    "isMultipart": true,
                    "isSendLogging": true,
                    "isStoppedOnJobError": false,
                    "modified": {
                        "name": "",
                        "date": ""
                    },
                    "preHeader": "Review the KN189 summary for KEYTRUDA.",
                    "priority": 4,
                    "sendClassificationId": "681c0b62-3d0f-ea11-a2db-1402ec938a50",
                    "throttleLimit": 0,
                    "throttleOpens": "1/1/0001 12:00:00 AM",
                    "throttleCloses": "1/1/0001 12:00:00 AM",
                    "deliveryProfileId": "671c0b62-3d0f-ea11-a2db-1402ec938a50",
                    "senderProfileId": "6a1c0b62-3d0f-ea11-a2db-1402ec938a50",
                    "isTrackingClicks": true,
                    "publicationListId": 5522
                },
                "triggeredSendKey": "224304",
                "applicationExtensionKey": "jb-email-activity",
                "isModified": false,
                "isSimulation": false,
                "googleAnalyticsCampaignName": "",
                "useLLTS": false,
                "fuelAgentRequested": false
            },
            "metaData": {
                "icon": "https://jb-email-activity.s7.marketingcloudapps.com/img/email-icon.svg",
                "iconSmall": "https://jb-email-activity.s7.marketingcloudapps.com/img/email-icon.svg",
                "category": "message",
                "version": "1.0",
                "statsContactIcon": "",
                "original_iconSmall": "/img/email-icon.svg",
                "original_icon": "/img/email-icon.svg",
                "sections": {},
                "isConfigured": true
            },
            "schema": {
                "arguments": {
                    "requestID": {
                        "dataType": "Text",
                        "isNullable": true,
                        "direction": "Out",
                        "readOnly": false,
                        "access": "Hidden"
                    },
                    "messageKey": {
                        "dataType": "Text",
                        "isNullable": true,
                        "direction": "Out",
                        "readOnly": false,
                        "access": "Hidden"
                    },
                    "activityId": {
                        "dataType": "Text",
                        "isNullable": true,
                        "direction": "In",
                        "readOnly": false,
                        "access": "Hidden"
                    },
                    "definitionId": {
                        "dataType": "Text",
                        "isNullable": true,
                        "direction": "In",
                        "readOnly": true,
                        "access": "Hidden"
                    },
                    "emailSubjectDataBound": {
                        "dataType": "Text",
                        "isNullable": true,
                        "direction": "In",
                        "readOnly": true,
                        "access": "Hidden"
                    },
                    "contactId": {
                        "dataType": "Number",
                        "isNullable": true,
                        "direction": "In",
                        "readOnly": false,
                        "access": "Hidden"
                    },
                    "contactKey": {
                        "dataType": "Text",
                        "isNullable": false,
                        "direction": "In",
                        "readOnly": false,
                        "access": "Hidden"
                    },
                    "emailAddress": {
                        "dataType": "Text",
                        "isNullable": false,
                        "direction": "In",
                        "readOnly": false,
                        "access": "Hidden"
                    },
                    "sourceCustomObjectId": {
                        "dataType": "Text",
                        "isNullable": true,
                        "direction": "In",
                        "readOnly": false,
                        "access": "Hidden"
                    },
                    "sourceCustomObjectKey": {
                        "dataType": "LongNumber",
                        "isNullable": true,
                        "direction": "In",
                        "readOnly": false,
                        "access": "Hidden"
                    },
                    "fieldType": {
                        "dataType": "Text",
                        "isNullable": true,
                        "direction": "In",
                        "readOnly": false,
                        "access": "Hidden"
                    },
                    "eventData": {
                        "dataType": "Text",
                        "isNullable": true,
                        "direction": "In",
                        "readOnly": false,
                        "access": "Hidden"
                    },
                    "obfuscationProperties": {
                        "dataType": "Text",
                        "isNullable": true,
                        "direction": "In",
                        "readOnly": false,
                        "access": "Hidden"
                    },
                    "customObjectKey": {
                        "dataType": "LongNumber",
                        "isNullable": true,
                        "direction": "In",
                        "readOnly": true,
                        "access": "Hidden"
                    },
                    "definitionInstanceId": {
                        "dataType": "Text",
                        "isNullable": false,
                        "direction": "In",
                        "readOnly": false,
                        "access": "Hidden"
                    }
                }
            }
        },
        {
            "id": "6d33eabd-a2e1-4a05-84c6-0462ee29efd5",
            "key": "WAITBYDURATION-5",
            "name": "1 minute",
            "description": "",
            "type": "WAIT",
            "outcomes": [
                {
                    "key": "7cdc1f28-fa75-4463-acc4-01f8c35e1a4d",
                    "arguments": {},
                    "metaData": {
                        "invalid": false
                    }
                }
            ],
            "arguments": {
                "waitEndDateAttributeDataBound": "",
                "waitDefinitionId": "96fb6539-954b-404a-8cb0-c2004df4b4a4",
                "waitForEventId": "",
                "executionMode": "{{Context.ExecutionMode}}",
                "startActivityKey": "{{Context.StartActivityKey}}",
                "waitQueueId": "{{Context.WaitQueueId}}"
            },
            "configurationArguments": {
                "waitDuration": 1,
                "waitUnit": "MINUTES",
                "specifiedTime": "00:00",
                "timeZone": "Singapore Standard Time",
                "description": "",
                "waitEndDateAttributeExpression": "",
                "specificDate": "",
                "waitForEventKey": ""
            },
            "metaData": {
                "isConfigured": true,
                "isExtended": false,
                "waitType": "duration",
                "guidanceCardKey": "",
                "uiType": "WAITBYDURATION"
            },
            "schema": {
                "arguments": {
                    "endDate": {
                        "dataType": "Date",
                        "isNullable": false,
                        "direction": "Out",
                        "readOnly": false,
                        "access": "Hidden"
                    },
                    "waitEndDateAttributeDataBound": {
                        "dataType": "Text",
                        "isNullable": true,
                        "direction": "In",
                        "readOnly": false,
                        "access": "Hidden"
                    },
                    "waitDefinitionId": {
                        "dataType": "Text",
                        "isNullable": false,
                        "direction": "In",
                        "readOnly": false,
                        "access": "Hidden"
                    },
                    "waitForEventId": {
                        "dataType": "Text",
                        "isNullable": true,
                        "direction": "In",
                        "readOnly": false,
                        "access": "Hidden"
                    },
                    "executionMode": {
                        "dataType": "Text",
                        "isNullable": false,
                        "direction": "In",
                        "readOnly": false,
                        "access": "Hidden"
                    },
                    "startActivityKey": {
                        "dataType": "Text",
                        "isNullable": true,
                        "direction": "In",
                        "readOnly": false,
                        "access": "Hidden"
                    },
                    "waitQueueId": {
                        "dataType": "LongNumber",
                        "isNullable": true,
                        "direction": "In",
                        "readOnly": false,
                        "access": "Hidden"
                    }
                }
            }
        }
    ],
    "triggers": [
        {
            "key": "TRIGGER",
            "name": "TRIGGER",
            "description": "",
            "type": "EmailAudience",
            "outcomes": [],
            "arguments": {
                "startActivityKey": "{{Context.StartActivityKey}}",
                "dequeueReason": "{{Context.DequeueReason}}",
                "lastExecutedActivityKey": "{{Context.LastExecutedActivityKey}}",
                "filterResult": "true"
            },
            "configurationArguments": {
                "schemaVersionId": 0,
                "criteria": "",
                "filterDefinitionId": "00000000-0000-0000-0000-000000000000"
            },
            "metaData": {
                "sourceInteractionId": "00000000-0000-0000-0000-000000000000",
                "eventDefinitionKey": "DEAudience-a4b53898-343f-9be7-5e77-3ce7f8a941e5",
                "chainType": "None",
                "configurationRequired": false,
                "iconUrl": "/images/icon-data-extension.svg",
                "title": "Data Extension",
                "entrySourceGroupConfigUrl": "jb:///data/entry/audience/entrysourcegroupconfig.json"
            }
        }
    ],
    "goals": [],
    "exits": [],
    "notifiers": [],
    "entryMode": "MultipleEntries",
    "definitionType": "Multistep",
    "channel": "",
    "defaults": {
        "email": [
            "{{Event.DEAudience-a4b53898-343f-9be7-5e77-3ce7f8a941e5.\"EMAIL\"}}"
        ],
        "properties": {
            "analyticsTracking": {
                "enabled": true,
                "analyticsType": "google",
                "urlDomainsToTrack": []
            }
        }
    },
    "metaData": {
        "dataSource": "ContactsModel"
    },
    "executionMode": "Production",
    "status": "Published",
    "scheduledStatus": "Draft",
    "r__folder_Path": "my journeys"
}
