{
    "key": "9a94ff27-5eb6-21fb-5b04-daad5962b140",
    "name": "Wave1_DR_NINS_PAED_TR_1 ",
    "lastPublishedDate": "2023-07-31T06:04:37",
    "description": "",
    "version": 1,
    "workflowApiVersion": 1,
    "createdDate": "2023-07-20T03:05:12.63",
    "modifiedDate": "2023-07-31T06:04:37.603",
    "activities": [
        {
            "id": "bcbcf9ab-b744-4792-bbb7-9937fa49967d",
            "key": "MULTICRITERIADECISIONV2-1",
            "name": "",
            "description": "",
            "type": "MULTICRITERIADECISION",
            "outcomes": [
                {
                    "key": "default_path_1",
                    "next": "STOWAIT-3",
                    "arguments": {},
                    "metaData": {
                        "label": "Call made",
                        "skipI18n": true,
                        "isLabelFromConversion": false,
                        "criteriaDescription": "Call is True",
                        "invalid": false
                    }
                },
                {
                    "key": "remainder_path",
                    "next": "STOWAIT-4",
                    "arguments": {},
                    "metaData": {
                        "label": "Call not made",
                        "skipI18n": true,
                        "isLabelFromConversion": false,
                        "invalid": false
                    }
                }
            ],
            "arguments": {
                "filterResult": "default_path_1={{Contact.FilterId.94ac4ef0-f8d0-4b8c-9ccd-8694b13c757a}},remainder_path=False"
            },
            "configurationArguments": {
                "schemaVersionId": 252,
                "criteria": {
                    "default_path_1": "<FilterDefinition><ConditionSet Operator=\"AND\" ConditionSetName=\"Individual Filter Grouping\"><Condition IsEphemeralAttribute=\"true\" Key=\"Event.DEAudience-7e075095-2dc0-659f-e8fd-8ffb1d29eb20.Call\" Operator=\"Is\" UiMetaData=\"{}\"><Value><![CDATA[true]]></Value></Condition></ConditionSet></FilterDefinition>"
                }
            },
            "metaData": {
                "isConfigured": true
            },
            "schema": {
                "arguments": {
                    "actualChoice": {
                        "dataType": "Number",
                        "isNullable": false,
                        "direction": "Out",
                        "readOnly": false,
                        "access": "Hidden"
                    },
                    "filterResult": {
                        "dataType": "Text",
                        "isNullable": false,
                        "direction": "In",
                        "readOnly": true,
                        "access": "Hidden"
                    }
                }
            }
        },
        {
            "id": "0a5cd9d1-c72a-4eb7-8197-1175fbcb867c",
            "key": "WAITBYDURATION-4",
            "name": "1 minute",
            "description": "",
            "type": "WAIT",
            "outcomes": [
                {
                    "key": "5778b8c9-d318-43fe-b19c-eab7a504477f",
                    "arguments": {},
                    "metaData": {
                        "invalid": false
                    }
                }
            ],
            "arguments": {
                "waitEndDateAttributeDataBound": "",
                "waitDefinitionId": "ddc61cec-3cd6-4d8f-ae5d-07f7fa91ce7d",
                "waitForEventId": "",
                "executionMode": "{{Context.ExecutionMode}}",
                "startActivityKey": "{{Context.StartActivityKey}}",
                "waitQueueId": "{{Context.WaitQueueId}}"
            },
            "configurationArguments": {
                "waitDuration": 1,
                "waitUnit": "MINUTES",
                "specifiedTime": "00:00",
                "timeZone": "India Standard Time",
                "description": "",
                "waitEndDateAttributeExpression": "",
                "specificDate": "",
                "waitForEventKey": ""
            },
            "metaData": {
                "isConfigured": true,
                "isExtended": false,
                "waitType": "duration",
                "guidanceCardKey": "",
                "uiType": "WAITBYDURATION"
            },
            "schema": {
                "arguments": {
                    "endDate": {
                        "dataType": "Date",
                        "isNullable": false,
                        "direction": "Out",
                        "readOnly": false,
                        "access": "Hidden"
                    },
                    "waitEndDateAttributeDataBound": {
                        "dataType": "Text",
                        "isNullable": true,
                        "direction": "In",
                        "readOnly": false,
                        "access": "Hidden"
                    },
                    "waitDefinitionId": {
                        "dataType": "Text",
                        "isNullable": false,
                        "direction": "In",
                        "readOnly": false,
                        "access": "Hidden"
                    },
                    "waitForEventId": {
                        "dataType": "Text",
                        "isNullable": true,
                        "direction": "In",
                        "readOnly": false,
                        "access": "Hidden"
                    },
                    "executionMode": {
                        "dataType": "Text",
                        "isNullable": false,
                        "direction": "In",
                        "readOnly": false,
                        "access": "Hidden"
                    },
                    "startActivityKey": {
                        "dataType": "Text",
                        "isNullable": true,
                        "direction": "In",
                        "readOnly": false,
                        "access": "Hidden"
                    },
                    "waitQueueId": {
                        "dataType": "LongNumber",
                        "isNullable": true,
                        "direction": "In",
                        "readOnly": false,
                        "access": "Hidden"
                    }
                }
            }
        },
        {
            "id": "dcfe69d2-48f8-4aca-8edb-456d9065d2e7",
            "key": "EMAILV2-5",
            "name": "TR_GSL_00068_Wave1_DR_REC-NINS-E3-SLB_BR_GULAM+PAED+TR",
            "description": "",
            "type": "EMAILV2",
            "outcomes": [
                {
                    "key": "3d5dc7ab-fff4-4400-9798-a6228bafe5c5",
                    "next": "WAITBYDURATION-5",
                    "arguments": {},
                    "metaData": {
                        "invalid": false
                    }
                }
            ],
            "arguments": {
                "activityId": "{{Activity.Id}}",
                "definitionId": "{{Context.DefinitionId}}",
                "emailSubjectDataBound": "GARDASIL®9 ile adölesan hastalarınızı HPV'den korumaya yardımcı olun",
                "contactId": "{{Contact.Id}}",
                "contactKey": "{{Contact.Key}}",
                "emailAddress": "{{InteractionDefaults.Email}}",
                "sourceCustomObjectId": "{{Contact.AddressInfo.Email.SourceCustomObjectId}}",
                "sourceCustomObjectKey": "{{Contact.AddressInfo.Email.SourceCustomObjectKey}}",
                "fieldType": "{{Contact.AddressInfo.Email.FieldType}}",
                "eventData": "{{Event}}",
                "obfuscationProperties": "{{InteractionDefaults.Email.ObfuscationProperties}}",
                "customObjectKey": "",
                "definitionInstanceId": "{{Context.DefinitionInstanceId}}"
            },
            "configurationArguments": {
                "triggeredSend": {
                    "autoAddSubscribers": true,
                    "autoUpdateSubscribers": true,
                    "bccEmail": "",
                    "campaigns": [
                        {
                            "id": 6252,
                            "name": "Wave 1",
                            "color": "#d7edad"
                        }
                    ],
                    "ccEmail": "",
                    "created": {
                        "name": "",
                        "date": ""
                    },
                    "domainExclusions": [],
                    "dynamicEmailSubject": "GARDASIL®9 ile adölesan hastalarınızı HPV'den korumaya yardımcı olun",
                    "emailId": 159842,
                    "emailSubject": "GARDASIL®9 ile adölesan hastalarınızı HPV'den korumaya yardımcı olun",
                    "exclusionFilter": "",
                    "isSalesforceTracking": false,
                    "isMultipart": true,
                    "isSendLogging": true,
                    "isStoppedOnJobError": false,
                    "modified": {
                        "name": "",
                        "date": ""
                    },
                    "preHeader": "Değerli %%FIRST_NAME%% %%Salutation%%",
                    "priority": 4,
                    "sendClassificationId": "8d4ac0f4-ea09-ea11-a2db-1402ec938a50",
                    "throttleLimit": 0,
                    "throttleOpens": "1/1/0001 12:00:00 AM",
                    "throttleCloses": "1/1/0001 12:00:00 AM",
                    "deliveryProfileId": "8c4ac0f4-ea09-ea11-a2db-1402ec938a50",
                    "senderProfileId": "3e4dc31e-f79a-ec11-a30f-1402ec938a6c",
                    "isTrackingClicks": true,
                    "publicationListId": 5509
                },
                "triggeredSendKey": "230957",
                "applicationExtensionKey": "jb-email-activity",
                "isModified": false,
                "isSimulation": false,
                "googleAnalyticsCampaignName": "",
                "useLLTS": false,
                "fuelAgentRequested": false
            },
            "metaData": {
                "isConfigured": true,
                "sections": {}
            },
            "schema": {
                "arguments": {
                    "requestID": {
                        "dataType": "Text",
                        "isNullable": true,
                        "direction": "Out",
                        "readOnly": false,
                        "access": "Hidden"
                    },
                    "messageKey": {
                        "dataType": "Text",
                        "isNullable": true,
                        "direction": "Out",
                        "readOnly": false,
                        "access": "Hidden"
                    },
                    "activityId": {
                        "dataType": "Text",
                        "isNullable": true,
                        "direction": "In",
                        "readOnly": false,
                        "access": "Hidden"
                    },
                    "definitionId": {
                        "dataType": "Text",
                        "isNullable": true,
                        "direction": "In",
                        "readOnly": true,
                        "access": "Hidden"
                    },
                    "emailSubjectDataBound": {
                        "dataType": "Text",
                        "isNullable": true,
                        "direction": "In",
                        "readOnly": true,
                        "access": "Hidden"
                    },
                    "contactId": {
                        "dataType": "Number",
                        "isNullable": true,
                        "direction": "In",
                        "readOnly": false,
                        "access": "Hidden"
                    },
                    "contactKey": {
                        "dataType": "Text",
                        "isNullable": false,
                        "direction": "In",
                        "readOnly": false,
                        "access": "Hidden"
                    },
                    "emailAddress": {
                        "dataType": "Text",
                        "isNullable": false,
                        "direction": "In",
                        "readOnly": false,
                        "access": "Hidden"
                    },
                    "sourceCustomObjectId": {
                        "dataType": "Text",
                        "isNullable": true,
                        "direction": "In",
                        "readOnly": false,
                        "access": "Hidden"
                    },
                    "sourceCustomObjectKey": {
                        "dataType": "LongNumber",
                        "isNullable": true,
                        "direction": "In",
                        "readOnly": false,
                        "access": "Hidden"
                    },
                    "fieldType": {
                        "dataType": "Text",
                        "isNullable": true,
                        "direction": "In",
                        "readOnly": false,
                        "access": "Hidden"
                    },
                    "eventData": {
                        "dataType": "Text",
                        "isNullable": true,
                        "direction": "In",
                        "readOnly": false,
                        "access": "Hidden"
                    },
                    "obfuscationProperties": {
                        "dataType": "Text",
                        "isNullable": true,
                        "direction": "In",
                        "readOnly": false,
                        "access": "Hidden"
                    },
                    "customObjectKey": {
                        "dataType": "LongNumber",
                        "isNullable": true,
                        "direction": "In",
                        "readOnly": true,
                        "access": "Hidden"
                    },
                    "definitionInstanceId": {
                        "dataType": "Text",
                        "isNullable": false,
                        "direction": "In",
                        "readOnly": false,
                        "access": "Hidden"
                    }
                }
            }
        },
        {
            "id": "0661744c-8b39-479e-9ce2-48b508003370",
            "key": "WAITUNTILSPECIFICDATE-1",
            "name": "August 7, 2023 3:00 PM",
            "description": "",
            "type": "WAIT",
            "outcomes": [
                {
                    "key": "90d153cd-ca8f-4d9f-a176-f11485ae485e",
                    "next": "MULTICRITERIADECISIONV2-2",
                    "arguments": {},
                    "metaData": {
                        "invalid": false
                    }
                }
            ],
            "arguments": {
                "waitEndDateAttributeDataBound": "",
                "waitDefinitionId": "194ffceb-d879-4f59-b5b5-27d5ae10b04b",
                "waitForEventId": "",
                "executionMode": "{{Context.ExecutionMode}}",
                "startActivityKey": "{{Context.StartActivityKey}}",
                "waitQueueId": "{{Context.WaitQueueId}}"
            },
            "configurationArguments": {
                "waitDuration": 0,
                "waitUnit": "",
                "specifiedTime": "15:00",
                "timeZone": "Arab Standard Time",
                "description": "",
                "waitEndDateAttributeExpression": "",
                "specificDate": "2023-08-07",
                "waitForEventKey": ""
            },
            "metaData": {
                "isConfigured": true,
                "waitType": "specifiedDate",
                "attribute": "",
                "uiType": "WAITUNTILSPECIFICDATE"
            },
            "schema": {
                "arguments": {
                    "endDate": {
                        "dataType": "Date",
                        "isNullable": false,
                        "direction": "Out",
                        "readOnly": false,
                        "access": "Hidden"
                    },
                    "waitEndDateAttributeDataBound": {
                        "dataType": "Text",
                        "isNullable": true,
                        "direction": "In",
                        "readOnly": false,
                        "access": "Hidden"
                    },
                    "waitDefinitionId": {
                        "dataType": "Text",
                        "isNullable": false,
                        "direction": "In",
                        "readOnly": false,
                        "access": "Hidden"
                    },
                    "waitForEventId": {
                        "dataType": "Text",
                        "isNullable": true,
                        "direction": "In",
                        "readOnly": false,
                        "access": "Hidden"
                    },
                    "executionMode": {
                        "dataType": "Text",
                        "isNullable": false,
                        "direction": "In",
                        "readOnly": false,
                        "access": "Hidden"
                    },
                    "startActivityKey": {
                        "dataType": "Text",
                        "isNullable": true,
                        "direction": "In",
                        "readOnly": false,
                        "access": "Hidden"
                    },
                    "waitQueueId": {
                        "dataType": "LongNumber",
                        "isNullable": true,
                        "direction": "In",
                        "readOnly": false,
                        "access": "Hidden"
                    }
                }
            }
        },
        {
            "id": "00098ec7-b062-4c32-817b-5acffdf16421",
            "key": "WAITBYDURATION-2",
            "name": "1 minute",
            "description": "",
            "type": "WAIT",
            "outcomes": [
                {
                    "key": "fd087c93-168f-4188-b609-baa27bed6f8f",
                    "arguments": {},
                    "metaData": {
                        "invalid": false
                    }
                }
            ],
            "arguments": {
                "waitEndDateAttributeDataBound": "",
                "waitDefinitionId": "0e2d0555-50a3-44fb-b8c7-115559c46703",
                "waitForEventId": "",
                "executionMode": "{{Context.ExecutionMode}}",
                "startActivityKey": "{{Context.StartActivityKey}}",
                "waitQueueId": "{{Context.WaitQueueId}}"
            },
            "configurationArguments": {
                "waitDuration": 1,
                "waitUnit": "MINUTES",
                "specifiedTime": "00:00",
                "timeZone": "India Standard Time",
                "description": "",
                "waitEndDateAttributeExpression": "",
                "specificDate": "",
                "waitForEventKey": ""
            },
            "metaData": {
                "isConfigured": true,
                "isExtended": false,
                "waitType": "duration",
                "guidanceCardKey": "",
                "uiType": "WAITBYDURATION"
            },
            "schema": {
                "arguments": {
                    "endDate": {
                        "dataType": "Date",
                        "isNullable": false,
                        "direction": "Out",
                        "readOnly": false,
                        "access": "Hidden"
                    },
                    "waitEndDateAttributeDataBound": {
                        "dataType": "Text",
                        "isNullable": true,
                        "direction": "In",
                        "readOnly": false,
                        "access": "Hidden"
                    },
                    "waitDefinitionId": {
                        "dataType": "Text",
                        "isNullable": false,
                        "direction": "In",
                        "readOnly": false,
                        "access": "Hidden"
                    },
                    "waitForEventId": {
                        "dataType": "Text",
                        "isNullable": true,
                        "direction": "In",
                        "readOnly": false,
                        "access": "Hidden"
                    },
                    "executionMode": {
                        "dataType": "Text",
                        "isNullable": false,
                        "direction": "In",
                        "readOnly": false,
                        "access": "Hidden"
                    },
                    "startActivityKey": {
                        "dataType": "Text",
                        "isNullable": true,
                        "direction": "In",
                        "readOnly": false,
                        "access": "Hidden"
                    },
                    "waitQueueId": {
                        "dataType": "LongNumber",
                        "isNullable": true,
                        "direction": "In",
                        "readOnly": false,
                        "access": "Hidden"
                    }
                }
            }
        },
        {
            "id": "b5d06cda-1d7b-41eb-8c6f-8ab268fb730d",
            "key": "STOWAIT-3",
            "name": "Einstein STO - 48 Hours",
            "description": "",
            "type": "STOWAIT",
            "outcomes": [
                {
                    "key": "ad6807c0-27e2-4f24-8c69-07c3cdf8e595",
                    "next": "EMAILV2-3",
                    "arguments": {},
                    "metaData": {
                        "invalid": false
                    }
                }
            ],
            "arguments": {
                "contactKey": "{{Context.ContactKey}}",
                "contactTagsIn": "{{Interaction.STOWAIT-3.ContactTagsOut}}",
                "scheduledExpireTimeIn": "{{Interaction.STOWAIT-3.ScheduledExpireTimeOut}}",
                "jbActivityId": "{{Activity.Id}}",
                "jbJourneyId": "{{Context.OriginalDefinitionId}}",
                "jbJourneyVersion": "{{Context.VersionNumber}}",
                "waitDefinitionId": "00000000-0000-0000-0000-000000000000",
                "waitForEventId": "",
                "executionMode": "{{Context.ExecutionMode}}",
                "startActivityKey": "{{Context.StartActivityKey}}",
                "waitQueueId": "{{Context.WaitQueueId}}"
            },
            "configurationArguments": {
                "applicationExtensionKey": "f828061a-5f0e-46a9-975e-18c414192d17",
                "params": {
                    "slidingWindowHours": 48,
                    "enableRandomTime": false,
                    "nextActivity": {
                        "id": "5e100d6a-db4a-4e4d-a117-b1cc2d95d6b0",
                        "key": "EMAILV2-3",
                        "type": "EMAILV2"
                    },
                    "version": 2,
                    "definitionType": "Multistep"
                },
                "overrideDateTime": "0001-01-01T06:00:00Z",
                "disableStoRestValidation": false,
                "disableFollowedByEmailValidation": false,
                "disableFollowedByPushNValidation": false,
                "waitForEventKey": ""
            },
            "metaData": {
                "backgroundColor": "#032e61",
                "category": "flow",
                "icon": "https://sto.us.sfmc-einstein.com/activity/static/media/Einstein_STO.png",
                "isConfigured": true,
                "iconSmall": "",
                "statsContactIcon": "",
                "original_icon": "static/media/Einstein_STO.png",
                "sections": {}
            },
            "schema": {
                "arguments": {
                    "contactTagsOut": {
                        "dataType": "Text",
                        "isNullable": true,
                        "direction": "Out",
                        "readOnly": false,
                        "access": "Hidden"
                    },
                    "scheduledExpireTimeOut": {
                        "dataType": "Date",
                        "isNullable": true,
                        "direction": "Out",
                        "readOnly": false,
                        "access": "Hidden"
                    },
                    "endDate": {
                        "dataType": "Date",
                        "isNullable": false,
                        "direction": "Out",
                        "readOnly": false,
                        "access": "Hidden"
                    },
                    "contactKey": {
                        "dataType": "Text",
                        "isNullable": false,
                        "direction": "In",
                        "readOnly": false,
                        "access": "Hidden"
                    },
                    "contactTagsIn": {
                        "dataType": "Text",
                        "isNullable": true,
                        "direction": "In",
                        "readOnly": false,
                        "access": "Hidden"
                    },
                    "scheduledExpireTimeIn": {
                        "dataType": "Date",
                        "isNullable": true,
                        "direction": "In",
                        "readOnly": false,
                        "access": "Hidden"
                    },
                    "jbActivityId": {
                        "dataType": "Text",
                        "isNullable": true,
                        "direction": "In",
                        "readOnly": false,
                        "access": "Hidden"
                    },
                    "jbJourneyId": {
                        "dataType": "Text",
                        "isNullable": true,
                        "direction": "In",
                        "readOnly": false,
                        "access": "Hidden"
                    },
                    "jbJourneyVersion": {
                        "dataType": "Number",
                        "isNullable": true,
                        "direction": "In",
                        "readOnly": false,
                        "access": "Hidden"
                    },
                    "waitDefinitionId": {
                        "dataType": "Text",
                        "isNullable": false,
                        "direction": "In",
                        "readOnly": false,
                        "access": "Hidden"
                    },
                    "waitForEventId": {
                        "dataType": "Text",
                        "isNullable": true,
                        "direction": "In",
                        "readOnly": false,
                        "access": "Hidden"
                    },
                    "executionMode": {
                        "dataType": "Text",
                        "isNullable": false,
                        "direction": "In",
                        "readOnly": false,
                        "access": "Hidden"
                    },
                    "startActivityKey": {
                        "dataType": "Text",
                        "isNullable": true,
                        "direction": "In",
                        "readOnly": false,
                        "access": "Hidden"
                    },
                    "waitQueueId": {
                        "dataType": "LongNumber",
                        "isNullable": true,
                        "direction": "In",
                        "readOnly": false,
                        "access": "Hidden"
                    }
                }
            }
        },
        {
            "id": "f8e99567-01b4-4c1d-a42d-9b9aea82f47d",
            "key": "MULTICRITERIADECISIONV2-2",
            "name": "",
            "description": "",
            "type": "MULTICRITERIADECISION",
            "outcomes": [
                {
                    "key": "default_path_1",
                    "next": "WAITBYDURATION-4",
                    "arguments": {},
                    "metaData": {
                        "label": "Email clicked",
                        "skipI18n": true,
                        "isLabelFromConversion": false,
                        "criteriaDescription": "EmailName contains TR_GSL_00068_Wave1_DR_REC-NINS-E2-SLB_BR_GULAM+PAED+TR AND URL contains https://www.msdsizinle.com/products/gardasil9/patient-recc.xhtml",
                        "invalid": false
                    }
                },
                {
                    "key": "remainder_path",
                    "next": "STOWAIT-5",
                    "arguments": {},
                    "metaData": {
                        "label": "Email not clicked",
                        "skipI18n": true,
                        "isLabelFromConversion": false,
                        "invalid": false
                    }
                }
            ],
            "arguments": {
                "filterResult": "default_path_1={{Contact.FilterId.14f554d9-fd9c-431e-b901-5456851d35a4}},remainder_path=False"
            },
            "configurationArguments": {
                "schemaVersionId": 252,
                "criteria": {
                    "default_path_1": "<FilterDefinition><ConditionSet Operator=\"AND\" ConditionSetName=\"Individual Filter Grouping\"><Condition Key=\"TR_NINS_DR_Click.EmailName\" Operator=\"Contains\" UiMetaData=\"{&quot;groupToSetRelationshipId&quot;:&quot;1276b4d3-5d2c-ee11-a5ca-5cba2c6f98e0&quot;}\"><AttributePath RelationshipID=\"ad120e13-5e2c-ee11-a5ca-5cba2c6f98e0\"><Value><![CDATA[TR_GSL_00068_Wave1_DR_REC-NINS-E2-SLB_BR_GULAM+PAED+TR]]></Value></AttributePath></Condition><Condition Key=\"TR_NINS_DR_Click.URL\" Operator=\"Contains\" UiMetaData=\"{&quot;groupToSetRelationshipId&quot;:&quot;1276b4d3-5d2c-ee11-a5ca-5cba2c6f98e0&quot;}\"><AttributePath RelationshipID=\"ad120e13-5e2c-ee11-a5ca-5cba2c6f98e0\"><Value><![CDATA[https://www.msdsizinle.com/products/gardasil9/patient-recc.xhtml]]></Value></AttributePath></Condition></ConditionSet></FilterDefinition>"
                }
            },
            "metaData": {
                "isConfigured": true
            },
            "schema": {
                "arguments": {
                    "actualChoice": {
                        "dataType": "Number",
                        "isNullable": false,
                        "direction": "Out",
                        "readOnly": false,
                        "access": "Hidden"
                    },
                    "filterResult": {
                        "dataType": "Text",
                        "isNullable": false,
                        "direction": "In",
                        "readOnly": true,
                        "access": "Hidden"
                    }
                }
            }
        },
        {
            "id": "5e100d6a-db4a-4e4d-a117-b1cc2d95d6b0",
            "key": "EMAILV2-3",
            "name": "TR_GSL_00068_Wave1_DR_REC-NINS-E1-SLA_BR_GULAM+PAED+TR",
            "description": "",
            "type": "EMAILV2",
            "outcomes": [
                {
                    "key": "aca18a36-20db-4934-8f20-e54b5ef0b671",
                    "next": "WAITBYDURATION-2",
                    "arguments": {},
                    "metaData": {
                        "invalid": false
                    }
                }
            ],
            "arguments": {
                "activityId": "{{Activity.Id}}",
                "definitionId": "{{Context.DefinitionId}}",
                "emailSubjectDataBound": "GARDASIL®9'u hastanızın aşılama programına ekleme zamanı geldi",
                "contactId": "{{Contact.Id}}",
                "contactKey": "{{Contact.Key}}",
                "emailAddress": "{{InteractionDefaults.Email}}",
                "sourceCustomObjectId": "{{Contact.AddressInfo.Email.SourceCustomObjectId}}",
                "sourceCustomObjectKey": "{{Contact.AddressInfo.Email.SourceCustomObjectKey}}",
                "fieldType": "{{Contact.AddressInfo.Email.FieldType}}",
                "eventData": "{{Event}}",
                "obfuscationProperties": "{{InteractionDefaults.Email.ObfuscationProperties}}",
                "customObjectKey": "",
                "definitionInstanceId": "{{Context.DefinitionInstanceId}}"
            },
            "configurationArguments": {
                "triggeredSend": {
                    "autoAddSubscribers": true,
                    "autoUpdateSubscribers": true,
                    "bccEmail": "",
                    "campaigns": [
                        {
                            "id": 6252,
                            "name": "Wave 1",
                            "color": "#d7edad"
                        }
                    ],
                    "ccEmail": "",
                    "created": {
                        "name": "",
                        "date": ""
                    },
                    "domainExclusions": [],
                    "dynamicEmailSubject": "GARDASIL®9'u hastanızın aşılama programına ekleme zamanı geldi",
                    "emailId": 159839,
                    "emailSubject": "GARDASIL®9'u hastanızın aşılama programına ekleme zamanı geldi",
                    "exclusionFilter": "",
                    "isSalesforceTracking": false,
                    "isMultipart": true,
                    "isSendLogging": true,
                    "isStoppedOnJobError": false,
                    "modified": {
                        "name": "",
                        "date": ""
                    },
                    "preHeader": "Değerli %%FIRST_NAME%% %%Salutation%%",
                    "priority": 4,
                    "sendClassificationId": "8d4ac0f4-ea09-ea11-a2db-1402ec938a50",
                    "throttleLimit": 0,
                    "throttleOpens": "1/1/0001 12:00:00 AM",
                    "throttleCloses": "1/1/0001 12:00:00 AM",
                    "deliveryProfileId": "8c4ac0f4-ea09-ea11-a2db-1402ec938a50",
                    "senderProfileId": "3e4dc31e-f79a-ec11-a30f-1402ec938a6c",
                    "isTrackingClicks": true,
                    "publicationListId": 5509
                },
                "triggeredSendKey": "230955",
                "applicationExtensionKey": "jb-email-activity",
                "isModified": false,
                "isSimulation": false,
                "googleAnalyticsCampaignName": "",
                "useLLTS": false,
                "fuelAgentRequested": false
            },
            "metaData": {
                "category": "message",
                "version": "1.0",
                "icon": "https://jb-email-activity.s7.marketingcloudapps.com/img/email-icon.svg",
                "iconSmall": "https://jb-email-activity.s7.marketingcloudapps.com/img/email-icon.svg",
                "statsContactIcon": "",
                "original_icon": "/img/email-icon.svg",
                "original_iconSmall": "/img/email-icon.svg",
                "sections": {},
                "isConfigured": true
            },
            "schema": {
                "arguments": {
                    "requestID": {
                        "dataType": "Text",
                        "isNullable": true,
                        "direction": "Out",
                        "readOnly": false,
                        "access": "Hidden"
                    },
                    "messageKey": {
                        "dataType": "Text",
                        "isNullable": true,
                        "direction": "Out",
                        "readOnly": false,
                        "access": "Hidden"
                    },
                    "activityId": {
                        "dataType": "Text",
                        "isNullable": true,
                        "direction": "In",
                        "readOnly": false,
                        "access": "Hidden"
                    },
                    "definitionId": {
                        "dataType": "Text",
                        "isNullable": true,
                        "direction": "In",
                        "readOnly": true,
                        "access": "Hidden"
                    },
                    "emailSubjectDataBound": {
                        "dataType": "Text",
                        "isNullable": true,
                        "direction": "In",
                        "readOnly": true,
                        "access": "Hidden"
                    },
                    "contactId": {
                        "dataType": "Number",
                        "isNullable": true,
                        "direction": "In",
                        "readOnly": false,
                        "access": "Hidden"
                    },
                    "contactKey": {
                        "dataType": "Text",
                        "isNullable": false,
                        "direction": "In",
                        "readOnly": false,
                        "access": "Hidden"
                    },
                    "emailAddress": {
                        "dataType": "Text",
                        "isNullable": false,
                        "direction": "In",
                        "readOnly": false,
                        "access": "Hidden"
                    },
                    "sourceCustomObjectId": {
                        "dataType": "Text",
                        "isNullable": true,
                        "direction": "In",
                        "readOnly": false,
                        "access": "Hidden"
                    },
                    "sourceCustomObjectKey": {
                        "dataType": "LongNumber",
                        "isNullable": true,
                        "direction": "In",
                        "readOnly": false,
                        "access": "Hidden"
                    },
                    "fieldType": {
                        "dataType": "Text",
                        "isNullable": true,
                        "direction": "In",
                        "readOnly": false,
                        "access": "Hidden"
                    },
                    "eventData": {
                        "dataType": "Text",
                        "isNullable": true,
                        "direction": "In",
                        "readOnly": false,
                        "access": "Hidden"
                    },
                    "obfuscationProperties": {
                        "dataType": "Text",
                        "isNullable": true,
                        "direction": "In",
                        "readOnly": false,
                        "access": "Hidden"
                    },
                    "customObjectKey": {
                        "dataType": "LongNumber",
                        "isNullable": true,
                        "direction": "In",
                        "readOnly": true,
                        "access": "Hidden"
                    },
                    "definitionInstanceId": {
                        "dataType": "Text",
                        "isNullable": false,
                        "direction": "In",
                        "readOnly": false,
                        "access": "Hidden"
                    }
                }
            }
        },
        {
            "id": "c27d038d-a2e2-4361-9e76-b7189491ca05",
            "key": "EMAILV2-4",
            "name": "TR_GSL_00068_Wave1_DR_REC-NINS-E2-SLB_BR_GULAM+PAED+TR",
            "description": "",
            "type": "EMAILV2",
            "outcomes": [
                {
                    "key": "1e03d99a-6112-4766-ae59-e0dc70ff61a2",
                    "next": "WAITUNTILSPECIFICDATE-1",
                    "arguments": {},
                    "metaData": {
                        "invalid": false
                    }
                }
            ],
            "arguments": {
                "activityId": "{{Activity.Id}}",
                "definitionId": "{{Context.DefinitionId}}",
                "emailSubjectDataBound": "GARDASIL®9 ile adölesan hastalarınızı HPV'den korumaya yardımcı olun",
                "contactId": "{{Contact.Id}}",
                "contactKey": "{{Contact.Key}}",
                "emailAddress": "{{InteractionDefaults.Email}}",
                "sourceCustomObjectId": "{{Contact.AddressInfo.Email.SourceCustomObjectId}}",
                "sourceCustomObjectKey": "{{Contact.AddressInfo.Email.SourceCustomObjectKey}}",
                "fieldType": "{{Contact.AddressInfo.Email.FieldType}}",
                "eventData": "{{Event}}",
                "obfuscationProperties": "{{InteractionDefaults.Email.ObfuscationProperties}}",
                "customObjectKey": "",
                "definitionInstanceId": "{{Context.DefinitionInstanceId}}"
            },
            "configurationArguments": {
                "triggeredSend": {
                    "autoAddSubscribers": true,
                    "autoUpdateSubscribers": true,
                    "bccEmail": "",
                    "campaigns": [
                        {
                            "id": 6252,
                            "name": "Wave 1",
                            "color": "#d7edad"
                        }
                    ],
                    "ccEmail": "",
                    "created": {
                        "name": "",
                        "date": ""
                    },
                    "domainExclusions": [],
                    "dynamicEmailSubject": "GARDASIL®9 ile adölesan hastalarınızı HPV'den korumaya yardımcı olun",
                    "emailId": 159841,
                    "emailSubject": "GARDASIL®9 ile adölesan hastalarınızı HPV'den korumaya yardımcı olun",
                    "exclusionFilter": "",
                    "isSalesforceTracking": false,
                    "isMultipart": true,
                    "isSendLogging": true,
                    "isStoppedOnJobError": false,
                    "modified": {
                        "name": "",
                        "date": ""
                    },
                    "preHeader": "Değerli %%FIRST_NAME%% %%Salutation%%",
                    "priority": 4,
                    "sendClassificationId": "8d4ac0f4-ea09-ea11-a2db-1402ec938a50",
                    "throttleLimit": 0,
                    "throttleOpens": "1/1/0001 12:00:00 AM",
                    "throttleCloses": "1/1/0001 12:00:00 AM",
                    "deliveryProfileId": "8c4ac0f4-ea09-ea11-a2db-1402ec938a50",
                    "senderProfileId": "3e4dc31e-f79a-ec11-a30f-1402ec938a6c",
                    "isTrackingClicks": true,
                    "publicationListId": 5509
                },
                "triggeredSendKey": "230956",
                "applicationExtensionKey": "jb-email-activity",
                "isModified": false,
                "isSimulation": false,
                "googleAnalyticsCampaignName": "",
                "useLLTS": false,
                "fuelAgentRequested": false
            },
            "metaData": {
                "category": "message",
                "version": "1.0",
                "icon": "https://jb-email-activity.s7.marketingcloudapps.com/img/email-icon.svg",
                "iconSmall": "https://jb-email-activity.s7.marketingcloudapps.com/img/email-icon.svg",
                "statsContactIcon": "",
                "original_icon": "/img/email-icon.svg",
                "original_iconSmall": "/img/email-icon.svg",
                "sections": {},
                "isConfigured": true
            },
            "schema": {
                "arguments": {
                    "requestID": {
                        "dataType": "Text",
                        "isNullable": true,
                        "direction": "Out",
                        "readOnly": false,
                        "access": "Hidden"
                    },
                    "messageKey": {
                        "dataType": "Text",
                        "isNullable": true,
                        "direction": "Out",
                        "readOnly": false,
                        "access": "Hidden"
                    },
                    "activityId": {
                        "dataType": "Text",
                        "isNullable": true,
                        "direction": "In",
                        "readOnly": false,
                        "access": "Hidden"
                    },
                    "definitionId": {
                        "dataType": "Text",
                        "isNullable": true,
                        "direction": "In",
                        "readOnly": true,
                        "access": "Hidden"
                    },
                    "emailSubjectDataBound": {
                        "dataType": "Text",
                        "isNullable": true,
                        "direction": "In",
                        "readOnly": true,
                        "access": "Hidden"
                    },
                    "contactId": {
                        "dataType": "Number",
                        "isNullable": true,
                        "direction": "In",
                        "readOnly": false,
                        "access": "Hidden"
                    },
                    "contactKey": {
                        "dataType": "Text",
                        "isNullable": false,
                        "direction": "In",
                        "readOnly": false,
                        "access": "Hidden"
                    },
                    "emailAddress": {
                        "dataType": "Text",
                        "isNullable": false,
                        "direction": "In",
                        "readOnly": false,
                        "access": "Hidden"
                    },
                    "sourceCustomObjectId": {
                        "dataType": "Text",
                        "isNullable": true,
                        "direction": "In",
                        "readOnly": false,
                        "access": "Hidden"
                    },
                    "sourceCustomObjectKey": {
                        "dataType": "LongNumber",
                        "isNullable": true,
                        "direction": "In",
                        "readOnly": false,
                        "access": "Hidden"
                    },
                    "fieldType": {
                        "dataType": "Text",
                        "isNullable": true,
                        "direction": "In",
                        "readOnly": false,
                        "access": "Hidden"
                    },
                    "eventData": {
                        "dataType": "Text",
                        "isNullable": true,
                        "direction": "In",
                        "readOnly": false,
                        "access": "Hidden"
                    },
                    "obfuscationProperties": {
                        "dataType": "Text",
                        "isNullable": true,
                        "direction": "In",
                        "readOnly": false,
                        "access": "Hidden"
                    },
                    "customObjectKey": {
                        "dataType": "LongNumber",
                        "isNullable": true,
                        "direction": "In",
                        "readOnly": true,
                        "access": "Hidden"
                    },
                    "definitionInstanceId": {
                        "dataType": "Text",
                        "isNullable": false,
                        "direction": "In",
                        "readOnly": false,
                        "access": "Hidden"
                    }
                }
            }
        },
        {
            "id": "8d89bc8a-67d1-4565-b805-d85834d797ab",
            "key": "STOWAIT-5",
            "name": "Einstein STO - 48 Hours",
            "description": "",
            "type": "STOWAIT",
            "outcomes": [
                {
                    "key": "914707ff-194e-4322-80ff-1aac68b38cb9",
                    "next": "EMAILV2-5",
                    "arguments": {},
                    "metaData": {
                        "invalid": false
                    }
                }
            ],
            "arguments": {
                "contactKey": "{{Context.ContactKey}}",
                "contactTagsIn": "{{Interaction.STOWAIT-5.ContactTagsOut}}",
                "scheduledExpireTimeIn": "{{Interaction.STOWAIT-5.ScheduledExpireTimeOut}}",
                "jbActivityId": "{{Activity.Id}}",
                "jbJourneyId": "{{Context.OriginalDefinitionId}}",
                "jbJourneyVersion": "{{Context.VersionNumber}}",
                "waitDefinitionId": "00000000-0000-0000-0000-000000000000",
                "waitForEventId": "",
                "executionMode": "{{Context.ExecutionMode}}",
                "startActivityKey": "{{Context.StartActivityKey}}",
                "waitQueueId": "{{Context.WaitQueueId}}"
            },
            "configurationArguments": {
                "applicationExtensionKey": "f828061a-5f0e-46a9-975e-18c414192d17",
                "params": {
                    "slidingWindowHours": 48,
                    "enableRandomTime": false,
                    "nextActivity": {
                        "id": "dcfe69d2-48f8-4aca-8edb-456d9065d2e7",
                        "key": "EMAILV2-5",
                        "type": "EMAILV2"
                    },
                    "version": 2,
                    "definitionType": "Multistep"
                },
                "overrideDateTime": "0001-01-01T06:00:00Z",
                "disableStoRestValidation": false,
                "disableFollowedByEmailValidation": false,
                "disableFollowedByPushNValidation": false,
                "waitForEventKey": ""
            },
            "metaData": {
                "backgroundColor": "#032e61",
                "category": "flow",
                "icon": "https://sto.us.sfmc-einstein.com/activity/static/media/Einstein_STO.png",
                "isConfigured": true,
                "iconSmall": "",
                "statsContactIcon": "",
                "original_icon": "static/media/Einstein_STO.png",
                "sections": {}
            },
            "schema": {
                "arguments": {
                    "contactTagsOut": {
                        "dataType": "Text",
                        "isNullable": true,
                        "direction": "Out",
                        "readOnly": false,
                        "access": "Hidden"
                    },
                    "scheduledExpireTimeOut": {
                        "dataType": "Date",
                        "isNullable": true,
                        "direction": "Out",
                        "readOnly": false,
                        "access": "Hidden"
                    },
                    "endDate": {
                        "dataType": "Date",
                        "isNullable": false,
                        "direction": "Out",
                        "readOnly": false,
                        "access": "Hidden"
                    },
                    "contactKey": {
                        "dataType": "Text",
                        "isNullable": false,
                        "direction": "In",
                        "readOnly": false,
                        "access": "Hidden"
                    },
                    "contactTagsIn": {
                        "dataType": "Text",
                        "isNullable": true,
                        "direction": "In",
                        "readOnly": false,
                        "access": "Hidden"
                    },
                    "scheduledExpireTimeIn": {
                        "dataType": "Date",
                        "isNullable": true,
                        "direction": "In",
                        "readOnly": false,
                        "access": "Hidden"
                    },
                    "jbActivityId": {
                        "dataType": "Text",
                        "isNullable": true,
                        "direction": "In",
                        "readOnly": false,
                        "access": "Hidden"
                    },
                    "jbJourneyId": {
                        "dataType": "Text",
                        "isNullable": true,
                        "direction": "In",
                        "readOnly": false,
                        "access": "Hidden"
                    },
                    "jbJourneyVersion": {
                        "dataType": "Number",
                        "isNullable": true,
                        "direction": "In",
                        "readOnly": false,
                        "access": "Hidden"
                    },
                    "waitDefinitionId": {
                        "dataType": "Text",
                        "isNullable": false,
                        "direction": "In",
                        "readOnly": false,
                        "access": "Hidden"
                    },
                    "waitForEventId": {
                        "dataType": "Text",
                        "isNullable": true,
                        "direction": "In",
                        "readOnly": false,
                        "access": "Hidden"
                    },
                    "executionMode": {
                        "dataType": "Text",
                        "isNullable": false,
                        "direction": "In",
                        "readOnly": false,
                        "access": "Hidden"
                    },
                    "startActivityKey": {
                        "dataType": "Text",
                        "isNullable": true,
                        "direction": "In",
                        "readOnly": false,
                        "access": "Hidden"
                    },
                    "waitQueueId": {
                        "dataType": "LongNumber",
                        "isNullable": true,
                        "direction": "In",
                        "readOnly": false,
                        "access": "Hidden"
                    }
                }
            }
        },
        {
            "id": "c4cd7dc3-1764-4726-8dbb-e41b6ac6cef0",
            "key": "WAITBYDURATION-5",
            "name": "1 minute",
            "description": "",
            "type": "WAIT",
            "outcomes": [
                {
                    "key": "6b0b9b82-c563-4963-9211-83c1e7ec058b",
                    "arguments": {},
                    "metaData": {
                        "invalid": false
                    }
                }
            ],
            "arguments": {
                "waitEndDateAttributeDataBound": "",
                "waitDefinitionId": "5280d1fb-f617-4164-ba48-b6ea17c6577e",
                "waitForEventId": "",
                "executionMode": "{{Context.ExecutionMode}}",
                "startActivityKey": "{{Context.StartActivityKey}}",
                "waitQueueId": "{{Context.WaitQueueId}}"
            },
            "configurationArguments": {
                "waitDuration": 1,
                "waitUnit": "MINUTES",
                "specifiedTime": "00:00",
                "timeZone": "India Standard Time",
                "description": "",
                "waitEndDateAttributeExpression": "",
                "specificDate": "",
                "waitForEventKey": ""
            },
            "metaData": {
                "isConfigured": true,
                "isExtended": false,
                "waitType": "duration",
                "guidanceCardKey": "",
                "uiType": "WAITBYDURATION"
            },
            "schema": {
                "arguments": {
                    "endDate": {
                        "dataType": "Date",
                        "isNullable": false,
                        "direction": "Out",
                        "readOnly": false,
                        "access": "Hidden"
                    },
                    "waitEndDateAttributeDataBound": {
                        "dataType": "Text",
                        "isNullable": true,
                        "direction": "In",
                        "readOnly": false,
                        "access": "Hidden"
                    },
                    "waitDefinitionId": {
                        "dataType": "Text",
                        "isNullable": false,
                        "direction": "In",
                        "readOnly": false,
                        "access": "Hidden"
                    },
                    "waitForEventId": {
                        "dataType": "Text",
                        "isNullable": true,
                        "direction": "In",
                        "readOnly": false,
                        "access": "Hidden"
                    },
                    "executionMode": {
                        "dataType": "Text",
                        "isNullable": false,
                        "direction": "In",
                        "readOnly": false,
                        "access": "Hidden"
                    },
                    "startActivityKey": {
                        "dataType": "Text",
                        "isNullable": true,
                        "direction": "In",
                        "readOnly": false,
                        "access": "Hidden"
                    },
                    "waitQueueId": {
                        "dataType": "LongNumber",
                        "isNullable": true,
                        "direction": "In",
                        "readOnly": false,
                        "access": "Hidden"
                    }
                }
            }
        },
        {
            "id": "10597c13-cc92-47bd-acc1-eb456d427d77",
            "key": "STOWAIT-4",
            "name": "Einstein STO - 48 Hours",
            "description": "",
            "type": "STOWAIT",
            "outcomes": [
                {
                    "key": "92ca43f6-d196-4d4a-99cc-f7d3b4889e05",
                    "next": "EMAILV2-4",
                    "arguments": {},
                    "metaData": {
                        "invalid": false
                    }
                }
            ],
            "arguments": {
                "contactKey": "{{Context.ContactKey}}",
                "contactTagsIn": "{{Interaction.STOWAIT-4.ContactTagsOut}}",
                "scheduledExpireTimeIn": "{{Interaction.STOWAIT-4.ScheduledExpireTimeOut}}",
                "jbActivityId": "{{Activity.Id}}",
                "jbJourneyId": "{{Context.OriginalDefinitionId}}",
                "jbJourneyVersion": "{{Context.VersionNumber}}",
                "waitDefinitionId": "00000000-0000-0000-0000-000000000000",
                "waitForEventId": "",
                "executionMode": "{{Context.ExecutionMode}}",
                "startActivityKey": "{{Context.StartActivityKey}}",
                "waitQueueId": "{{Context.WaitQueueId}}"
            },
            "configurationArguments": {
                "applicationExtensionKey": "f828061a-5f0e-46a9-975e-18c414192d17",
                "params": {
                    "slidingWindowHours": 48,
                    "enableRandomTime": false,
                    "nextActivity": {
                        "id": "c27d038d-a2e2-4361-9e76-b7189491ca05",
                        "key": "EMAILV2-4",
                        "type": "EMAILV2"
                    },
                    "version": 2,
                    "definitionType": "Multistep"
                },
                "overrideDateTime": "0001-01-01T06:00:00Z",
                "disableStoRestValidation": false,
                "disableFollowedByEmailValidation": false,
                "disableFollowedByPushNValidation": false,
                "waitForEventKey": ""
            },
            "metaData": {
                "backgroundColor": "#032e61",
                "category": "flow",
                "icon": "https://sto.us.sfmc-einstein.com/activity/static/media/Einstein_STO.png",
                "isConfigured": true,
                "iconSmall": "",
                "statsContactIcon": "",
                "original_icon": "static/media/Einstein_STO.png",
                "sections": {}
            },
            "schema": {
                "arguments": {
                    "contactTagsOut": {
                        "dataType": "Text",
                        "isNullable": true,
                        "direction": "Out",
                        "readOnly": false,
                        "access": "Hidden"
                    },
                    "scheduledExpireTimeOut": {
                        "dataType": "Date",
                        "isNullable": true,
                        "direction": "Out",
                        "readOnly": false,
                        "access": "Hidden"
                    },
                    "endDate": {
                        "dataType": "Date",
                        "isNullable": false,
                        "direction": "Out",
                        "readOnly": false,
                        "access": "Hidden"
                    },
                    "contactKey": {
                        "dataType": "Text",
                        "isNullable": false,
                        "direction": "In",
                        "readOnly": false,
                        "access": "Hidden"
                    },
                    "contactTagsIn": {
                        "dataType": "Text",
                        "isNullable": true,
                        "direction": "In",
                        "readOnly": false,
                        "access": "Hidden"
                    },
                    "scheduledExpireTimeIn": {
                        "dataType": "Date",
                        "isNullable": true,
                        "direction": "In",
                        "readOnly": false,
                        "access": "Hidden"
                    },
                    "jbActivityId": {
                        "dataType": "Text",
                        "isNullable": true,
                        "direction": "In",
                        "readOnly": false,
                        "access": "Hidden"
                    },
                    "jbJourneyId": {
                        "dataType": "Text",
                        "isNullable": true,
                        "direction": "In",
                        "readOnly": false,
                        "access": "Hidden"
                    },
                    "jbJourneyVersion": {
                        "dataType": "Number",
                        "isNullable": true,
                        "direction": "In",
                        "readOnly": false,
                        "access": "Hidden"
                    },
                    "waitDefinitionId": {
                        "dataType": "Text",
                        "isNullable": false,
                        "direction": "In",
                        "readOnly": false,
                        "access": "Hidden"
                    },
                    "waitForEventId": {
                        "dataType": "Text",
                        "isNullable": true,
                        "direction": "In",
                        "readOnly": false,
                        "access": "Hidden"
                    },
                    "executionMode": {
                        "dataType": "Text",
                        "isNullable": false,
                        "direction": "In",
                        "readOnly": false,
                        "access": "Hidden"
                    },
                    "startActivityKey": {
                        "dataType": "Text",
                        "isNullable": true,
                        "direction": "In",
                        "readOnly": false,
                        "access": "Hidden"
                    },
                    "waitQueueId": {
                        "dataType": "LongNumber",
                        "isNullable": true,
                        "direction": "In",
                        "readOnly": false,
                        "access": "Hidden"
                    }
                }
            }
        }
    ],
    "triggers": [
        {
            "key": "TRIGGER",
            "name": "Wave1_DR_NINS_PAED_TR_1 ",
            "description": "",
            "type": "EmailAudience",
            "outcomes": [],
            "arguments": {
                "startActivityKey": "{{Context.StartActivityKey}}",
                "dequeueReason": "{{Context.DequeueReason}}",
                "lastExecutedActivityKey": "{{Context.LastExecutedActivityKey}}",
                "filterResult": "true"
            },
            "configurationArguments": {
                "schemaVersionId": 0,
                "criteria": "",
                "filterDefinitionId": "00000000-0000-0000-0000-000000000000"
            },
            "metaData": {
                "sourceInteractionId": "00000000-0000-0000-0000-000000000000",
                "eventDefinitionKey": "DEAudience-7e075095-2dc0-659f-e8fd-8ffb1d29eb20",
                "chainType": "None",
                "configurationRequired": false,
                "iconUrl": "/images/icon-data-extension.svg",
                "title": "Data Extension",
                "category": "Audience",
                "entrySourceGroupConfigUrl": "jb:///data/entry/audience/entrysourcegroupconfig.json"
            }
        }
    ],
    "goals": [],
    "exits": [],
    "notifiers": [],
    "tags": [
        {
            "name": "MOTF"
        }
    ],
    "entryMode": "OnceAndDone",
    "definitionType": "Multistep",
    "channel": "",
    "defaults": {
        "email": [
            "{{Event.DEAudience-7e075095-2dc0-659f-e8fd-8ffb1d29eb20.\"EMAIL\"}}"
        ],
        "properties": {
            "analyticsTracking": {
                "enabled": true,
                "analyticsType": "google",
                "urlDomainsToTrack": []
            }
        }
    },
    "metaData": {
        "dataSource": "ContactsModel"
    },
    "executionMode": "Production",
    "status": "Published",
    "scheduledStatus": "Draft",
    "r__folder_Path": "my journeys/Turkey/HPV"
}
